LICENSE.txt
README.md
setup.py
D8N8D/D8N8D.py
D8N8D/__init__.py
D8N8D.egg-info/PKG-INFO
D8N8D.egg-info/SOURCES.txt
D8N8D.egg-info/dependency_links.txt
D8N8D.egg-info/top_level.txt