Metadata-Version: 2.1
Name: D8N8D
Version: 1.0.0
Summary: An unstoppable exit method for Python
Home-page: https://github.com/shridhuu
Author: Shridhar
Author-email: shridhuu166@gmail.com
Classifier: Programming Language :: Python :: 3
Classifier: License :: OSI Approved :: MIT License
Classifier: Operating System :: OS Independent
Requires-Python: >=3.6
License-File: LICENSE.txt
